fastapi_jinja/__init__.py
fastapi_jinja/engine.py
fastapi_jinja/exceptions.py
fastapi_jinja-0.2.0.dist-info/LICENSE
fastapi_jinja-0.2.0.dist-info/METADATA
fastapi_jinja-0.2.0.dist-info/WHEEL
fastapi_jinja-0.2.0.dist-info/top_level.txt
fastapi_jinja-0.2.0.dist-info/RECORD
